{"nodes": [{"id": "contributing_document", "label": "CONTRIBUTING.md Guide", "file_type": "document", "source_file": "CONTRIBUTING.md", "source_location": null, "source_url": null, "captured_at": null, "author": null, "contributor": null}, {"id": "contributing_bigint", "label": "BigInt XP Rule", "file_type": "rationale", "source_file": "CONTRIBUTING.md", "source_location": null, "source_url": null, "captured_at": null, "author": null, "contributor": null}, {"id": "contributing_window_bridge", "label": "Window Bridge Pattern", "file_type": "rationale", "source_file": "CONTRIBUTING.md", "source_location": null, "source_url": null, "captured_at": null, "author": null, "contributor": null}, {"id": "contributing_button_first", "label": "Button-First Testing", "file_type": "rationale", "source_file": "CONTRIBUTING.md", "source_location": null, "source_url": null, "captured_at": null, "author": null, "contributor": null}], "edges": [{"source": "contributing_document", "target": "contributing_bigint", "relation": "references", "confidence": "EXTRACTED", "confidence_score": 1.0, "source_file": "CONTRIBUTING.md", "source_location": null, "weight": 1.0}, {"source": "contributing_document", "target": "contributing_window_bridge", "relation": "references", "confidence": "EXTRACTED", "confidence_score": 1.0, "source_file": "CONTRIBUTING.md", "source_location": null, "weight": 1.0}, {"source": "contributing_document", "target": "contributing_button_first", "relation": "references", "confidence": "EXTRACTED", "confidence_score": 1.0, "source_file": "CONTRIBUTING.md", "source_location": null, "weight": 1.0}], "hyperedges": []}